AUTHORS
CHANGES
LICENSE
MANIFEST.in
README.rst
setup.py
codingsoho_tracking.egg-info/PKG-INFO
codingsoho_tracking.egg-info/SOURCES.txt
codingsoho_tracking.egg-info/dependency_links.txt
codingsoho_tracking.egg-info/requires.txt
codingsoho_tracking.egg-info/top_level.txt
tracking/__init__.py
tracking/admin.py
tracking/listeners.py
tracking/middleware.py
tracking/models.py
tracking/urls.py
tracking/utils.py
tracking/views.py
tracking/locale/de/LC_MESSAGES/django.mo
tracking/locale/de/LC_MESSAGES/django.po
tracking/locale/zh/LC_MESSAGES/django.mo
tracking/locale/zh/LC_MESSAGES/django.po
tracking/media/tracking/img/Flags.zip
tracking/media/tracking/img/famfamfam_flag_icons.zip
tracking/media/tracking/js/jquery-1.4.4.min.js
tracking/migrations/0001_initial.py
tracking/migrations/0002_auto_20141023_0732.py
tracking/migrations/0003_auto_20141023_0834.py
tracking/migrations/__init__.py
tracking/south_migrations/0001_initial.py
tracking/south_migrations/__init__.py
tracking/templates/base.html
tracking/templates/tracking/_active_users.html
tracking/templates/tracking/_active_users.js
tracking/templates/tracking/refresh_active_users.js
tracking/templates/tracking/visitor_map.html
tracking/templatetags/__init__.py
tracking/templatetags/tracking_tags.py