Metadata-Version: 1.2
Name: codingsoho-tracking
Version: 0.4.1
Summary: Basic visitor tracking and blacklisting for Django
Home-page: http://github.com/hordechief/codingsoho-tracking/
Author: Horce Chief, Josh VanderLinden
Author-email: hordechief@qq.com
Maintainer: Horde Chief
Maintainer-email: hordechief@qq.com
License: MIT License
Keywords: django,tracking,visitors
Platform: UNKNOWN
Classifier: Development Status :: 5 - Production/Stable
Classifier: Environment :: Web Environment
Classifier: Framework :: Django
Classifier: Intended Audience :: Developers
Classifier: Intended Audience :: Information Technology
Classifier: Intended Audience :: System Administrators
Classifier: License :: OSI Approved :: MIT License
Classifier: Natural Language :: English
Classifier: Operating System :: OS Independent
Classifier: Programming Language :: Python
Classifier: Topic :: Internet :: Log Analysis
Classifier: Topic :: Internet :: WWW/HTTP :: Dynamic Content
Classifier: Topic :: Internet :: WWW/HTTP :: Dynamic Content :: Page Counters
Classifier: Topic :: Internet :: WWW/HTTP :: WSGI :: Middleware
Classifier: Topic :: Security
Classifier: Topic :: System :: Monitoring
Classifier: Topic :: Utilities
